mindelec/__init__.py
mindelec/_c_minddata.cpython-37m-aarch64-linux-gnu.so
mindelec/setup.py
mindelec/architecture/__init__.py
mindelec/architecture/activation.py
mindelec/architecture/basic_block.py
mindelec/architecture/mtl_weighted_loss.py
mindelec/architecture/util.py
mindelec/common/__init__.py
mindelec/common/constants.py
mindelec/common/lr_scheduler.py
mindelec/common/metrics.py
mindelec/data/__init__.py
mindelec/data/boundary.py
mindelec/data/data_base.py
mindelec/data/dataset.py
mindelec/data/equation.py
mindelec/data/existed_data.py
mindelec/data/pointcloud/__init__.py
mindelec/data/pointcloud/pointcloud.py
mindelec/data/pointcloud/pointcloud_util.py
mindelec/geometry/__init__.py
mindelec/geometry/csg.py
mindelec/geometry/geometry_1d.py
mindelec/geometry/geometry_2d.py
mindelec/geometry/geometry_3d.py
mindelec/geometry/geometry_base.py
mindelec/geometry/geometry_nd.py
mindelec/geometry/geometry_td.py
mindelec/geometry/utils.py
mindelec/lib/libglog.so.0
mindelec/loss/__init__.py
mindelec/loss/constraints.py
mindelec/loss/losses.py
mindelec/loss/net_with_loss.py
mindelec/operators/__init__.py
mindelec/operators/derivatives.py
mindelec/solver/__init__.py
mindelec/solver/callback.py
mindelec/solver/problem.py
mindelec/solver/solver.py
mindelec/vision/__init__.py
mindelec/vision/body.py
mindelec/vision/mindinsight_vision.py
mindelec/vision/plane.py
mindelec/vision/print_scatter.py
mindelec/vision/video.py
mindelec_ascend-0.2.0rc1.dist-info/METADATA
mindelec_ascend-0.2.0rc1.dist-info/WHEEL
mindelec_ascend-0.2.0rc1.dist-info/top_level.txt
mindelec_ascend-0.2.0rc1.dist-info/RECORD
